klever/__init__.py
klever-0.1.0a1.dist-info/WHEEL
klever-0.1.0a1.dist-info/entry_points.txt
klever-0.1.0a1.dist-info/METADATA
klever-0.1.0a1.dist-info/RECORD
