Metadata-Version: 2.3
Name: klever
Version: 0.1.0a1
Summary: Kit for Less-Effort Verification
Keywords: verification,UVM,SystemVerilog,cocotb,HDL,RTL,FPGA,ASIC,EDA
Author: esynr3z
Author-email: esynr3z <esynr3z@gmail.com>
License: Apache-2.0
Classifier: Programming Language :: Python
Classifier: Programming Language :: Python :: 3
Classifier: Programming Language :: Python :: 3.12
Classifier: Programming Language :: Python :: 3.13
Classifier: Programming Language :: Python :: 3.14
Classifier: Intended Audience :: Developers
Classifier: License :: OSI Approved :: Apache Software License
Classifier: Operating System :: OS Independent
Classifier: Topic :: Scientific/Engineering :: Electronic Design Automation (EDA)
Requires-Python: >=3.12, <3.15
Project-URL: Organization, https://github.com/klever-verif
Project-URL: Repository, https://github.com/klever-verif/klever.git
